{
  "problem_type": "finite_horizon",
  "optimization": "min",
  "initial_state": "S0",
  "terminal_values": {
    "T1": 0,
    "T2": 0
  },
  "stages": [
    {
      "name": "1",
      "states": [
        "S0"
      ],
      "transitions": [
        {
          "state": "S0",
          "decision": "A",
          "next_state": "S1",
          "value": 5
        },
        {
          "state": "S0",
          "decision": "B",
          "next_state": "S2",
          "value": 3
        }
      ]
    },
    {
      "name": "2",
      "states": [
        "S1",
        "S2"
      ],
      "transitions": [
        {
          "state": "S1",
          "decision": "C",
          "next_state": "T1",
          "value": 4
        },
        {
          "state": "S1",
          "decision": "D",
          "next_state": "T2",
          "value": 7
        },
        {
          "state": "S2",
          "decision": "E",
          "next_state": "T1",
          "value": 6
        },
        {
          "state": "S2",
          "decision": "F",
          "next_state": "T2",
          "value": 2
        }
      ]
    }
  ]
}
